objtyping/__init__.py
objtyping/objtyping.py
objtyping-0.5.4.dist-info/LICENSE
objtyping-0.5.4.dist-info/METADATA
objtyping-0.5.4.dist-info/WHEEL
objtyping-0.5.4.dist-info/top_level.txt
objtyping-0.5.4.dist-info/RECORD
