Metadata-Version: 2.1
Name: objtyping
Version: 0.5.4
Summary: convert a primitive dict-list data structure to/from an instance of user-defined class.
Author: Song Hui
Author-email: songofhawk@gmail.com
License: MIT
Classifier: Programming Language :: Python :: 3
Classifier: License :: OSI Approved :: MIT License
Classifier: Operating System :: OS Independent
License-File: LICENSE
